ci_diff_helper/__init__.py
ci_diff_helper/_config_base.py
ci_diff_helper/_github.py
ci_diff_helper/_utils.py
ci_diff_helper/appveyor.py
ci_diff_helper/circle_ci.py
ci_diff_helper/environment_vars.py
ci_diff_helper/git_tools.py
ci_diff_helper/travis.py
ci_diff_helper-0.2.0.dist-info/DESCRIPTION.rst
ci_diff_helper-0.2.0.dist-info/METADATA
ci_diff_helper-0.2.0.dist-info/RECORD
ci_diff_helper-0.2.0.dist-info/WHEEL
ci_diff_helper-0.2.0.dist-info/metadata.json
ci_diff_helper-0.2.0.dist-info/top_level.txt
ci_diff_helper-0.2.0.dist-info/zip-safe
tests/__init__.py
tests/test__config_base.py
tests/test__github.py
tests/test__init__.py
tests/test__utils.py
tests/test_appveyor.py
tests/test_circle_ci.py
tests/test_git_tools.py
tests/test_travis.py
tests/utils.py
