Metadata-Version: 2.0
Name: ci-diff-helper
Version: 0.2.0
Summary: Diff Helper for Continuous Integration (CI) Services
Home-page: https://github.com/dhermes/ci-diff-helper
Author: Danny Hermes
Author-email: daniel.j.hermes@gmail.com
License: Apache 2.0
Platform: Posix; MacOS X; Windows
Classifier: Development Status :: 3 - Alpha
Classifier: Intended Audience :: Developers
Classifier: License :: OSI Approved :: Apache Software License
Classifier: Operating System :: OS Independent
Classifier: Programming Language :: Python :: 2
Classifier: Programming Language :: Python :: 2.7
Classifier: Programming Language :: Python :: 3
Classifier: Programming Language :: Python :: 3.4
Classifier: Programming Language :: Python :: 3.5
Classifier: Topic :: Internet
Requires-Dist: enum34
Requires-Dist: requests
Requires-Dist: six (>=1.9.0)
